fpilot/__init__.py
fpilot/common.py
fpilot/checkpoints/__init__.py
fpilot/checkpoints/checkpoint.py
fpilot/opt_utils/__init__.py
fpilot/opt_utils/freezer.py
fpilot/trackers/__init__.py
fpilot/trackers/basic_trackers.py
fpilot/training/__init__.py
fpilot/training/trainer.py
flax_pilot_cpu-0.1.0.dist-info/LICENSE
flax_pilot_cpu-0.1.0.dist-info/METADATA
flax_pilot_cpu-0.1.0.dist-info/WHEEL
flax_pilot_cpu-0.1.0.dist-info/top_level.txt
flax_pilot_cpu-0.1.0.dist-info/RECORD
