Metadata-Version: 2.1
Name: flax-pilot-cpu
Version: 0.1.0
Summary: A Simplistic trainer for Flax
Home-page: https://github.com/NITHISHM2410/flax-pilot
Author: Nithish M
Author-email: nithishm2206@gmail.com
Classifier: Programming Language :: Python :: 3
Classifier: License :: OSI Approved :: MIT License
Classifier: Operating System :: OS Independent
Requires-Python: >=3.6
License-File: LICENSE
Requires-Dist: jax >=0.4.26
Requires-Dist: flax >=0.8.4
Requires-Dist: optax
Requires-Dist: numpy
Requires-Dist: tqdm
Requires-Dist: mergedeep
Requires-Dist: typing
Requires-Dist: orbax-checkpoint >=0.5.15
